{
  "directory": {
    "item": [
      {
        "last-modified": "2015-05-15 16:01:47",
        "name": "0000950123-15-006438-index-headers.html",
        "size": "",
        "type": "text.gif"
      },
      {
        "last-modified": "2015-05-15 16:01:47",
        "name": "0000950123-15-006438-index.html",
        "size": "",
        "type": "text.gif"
      },
      {
        "last-modified": "2015-05-15 16:01:47",
        "name": "0000950123-15-006438.txt",
        "size": "",
        "type": "text.gif"
      },
      {
        "last-modified": "2015-05-15 16:01:47",
        "name": "form13fInfoTable.xml",
        "size": "83226",
        "type": "text.gif"
      },
      {
        "last-modified": "2015-05-15 16:01:47",
        "name": "primary_doc.xml",
        "size": "5883",
        "type": "text.gif"
      }
    ],
    "name": "/Archives/edgar/data/1067983/000095012315006438",
    "parent-dir": "/Archives/edgar/data/1067983"
  }
}
