{
  "directory": {
    "item": [
      {
        "last-modified": "2003-09-23 12:07:20",
        "name": "0000950150-03-001058-index-headers.html",
        "size": "",
        "type": "text.gif"
      },
      {
        "last-modified": "2003-09-23 12:07:20",
        "name": "0000950150-03-001058-index.html",
        "size": "",
        "type": "text.gif"
      },
      {
        "last-modified": "2003-09-23 12:07:20",
        "name": "0000950150-03-001058.txt",
        "size": "",
        "type": "text.gif"
      },
      {
        "last-modified": "2003-09-23 12:07:20",
        "name": "a93172a2e13fvhrza.txt",
        "size": "7453",
        "type": "text.gif"
      }
    ],
    "name": "/Archives/edgar/data/1067983/000095015003001058",
    "parent-dir": "/Archives/edgar/data/1067983"
  }
}
